{"frameRate":60,"isGlobal":0,"armature":[{"bone":[{"name":"root","transform":{"y":-46.2721,"x":20.1671}},{"length":43,"transform":{"y":61.5721,"skX":-90,"skY":-90,"x":-29.7171},"parent":"root","name":"deluyi"},{"length":24,"transform":{"y":-18.45,"skX":-171.076,"skY":-171.076,"x":-14.65},"parent":"deluyi","name":"leftleg"},{"length":21,"transform":{"y":44.6,"skX":173.2825,"skY":173.2825,"x":-16.55},"parent":"deluyi","name":"rightleg"},{"length":74,"transform":{"y":56.05,"skX":152.1186,"skY":152.1186,"x":54.8},"parent":"deluyi","name":"rightarm"},{"length":82,"transform":{"y":-23.55,"skX":-144.0951,"skY":-144.0951,"x":58.6},"parent":"deluyi","name":"leftarm"},{"length":82,"transform":{"y":-0.15,"skX":15.6128,"skY":15.6128,"x":43.3},"parent":"deluyi","name":"head"},{"length":46,"transform":{"y":-8.5,"skX":6.4426,"skY":6.4426,"x":-4.15},"parent":"deluyi","name":"body"},{"length":35,"transform":{"y":9.3094,"skX":-128.4232,"skY":-128.4232,"x":28.9227},"parent":"head","name":"downmouth"}],"aabb":{"width":241.00000000000006,"y":-151.7466601078592,"height":212.47456171351496,"x":-100.33289246329097},"type":"Armature","name":"druid","skin":[{"slot":[{"display":[{"path":"desc_04","type":"image","name":"desc_04","transform":{"y":-59.8843,"skX":78.8576,"skY":78.8576,"x":5.8091}}],"name":"desc_04"},{"display":[{"path":"body","type":"image","name":"body","transform":{"y":17.3634,"skX":83.5574,"skY":83.5574,"x":30.8653}}],"name":"body"},{"display":[{"path":"desc_02","type":"image","name":"desc_02","transform":{"y":22.9409,"skX":78.8576,"skY":78.8576,"x":-5.906}}],"name":"desc_02"},{"display":[{"path":"header","type":"image","name":"header","transform":{"y":3.1625,"skX":78.8576,"skY":78.8576,"x":71.2258}}],"name":"header"},{"display":[{"path":"righteye_01","type":"image","name":"righteye_01","transform":{"y":19.4702,"skX":78.8576,"skY":78.8576,"x":47.9383}},{"path":"righteye_02","type":"image","name":"righteye_02","transform":{"y":19.4702,"skX":78.8576,"skY":78.8576,"x":47.9383}}],"name":"righteye_01"},{"display":[{"path":"rightarm","type":"image","name":"rightarm","transform":{"y":-3.0942,"skX":-62.1186,"skY":-62.1186,"x":42.6226}}],"name":"rightarm"},{"display":[{"path":"rightleg","type":"image","name":"rightleg","transform":{"y":-0.4792,"skX":-83.2825,"skY":-83.2825,"x":14.0303}}],"name":"rightleg"},{"display":[{"path":"upmouth","type":"image","name":"upmouth","transform":{"y":-14.6992,"skX":78.8576,"skY":78.8576,"x":32.545}}],"name":"upmouth"},{"display":[{"path":"leftarm","type":"image","name":"leftarm","transform":{"y":0.9853,"skX":-125.9049,"skY":-125.9049,"x":36.5506}}],"name":"leftarm"},{"display":[{"path":"desc_03","type":"image","name":"desc_03","transform":{"y":-36.0173,"skX":78.8576,"skY":78.8576,"x":-14.4608}}],"name":"desc_03"},{"display":[{"path":"beard","type":"image","name":"beard","transform":{"y":9.8963,"skX":78.8576,"skY":78.8576,"x":26.6876}}],"name":"beard"},{"display":[{"path":"desc_01","type":"image","name":"desc_01","transform":{"y":56.2704,"skX":78.8576,"skY":78.8576,"x":24.1005}}],"name":"desc_01"},{"display":[{"path":"lefteye_01","type":"image","name":"lefteye_01","transform":{"y":-35.0654,"skX":78.8576,"skY":78.8576,"x":42.8026}},{"path":"lefteye_02","type":"image","name":"lefteye_02","transform":{"y":-35.0654,"skX":78.8576,"skY":78.8576,"x":42.8026}}],"name":"lefteye_01"},{"display":[{"path":"weapon","type":"image","name":"weapon","transform":{"y":83.7547,"skX":83.5574,"skY":83.5574,"x":111.323}}],"name":"weapon"},{"display":[{"path":"leftleg","type":"image","name":"leftleg","transform":{"y":3.7311,"skX":-98.924,"skY":-98.924,"x":17.0632}}],"name":"leftleg"},{"display":[{"path":"downmouth","type":"image","name":"downmouth","transform":{"y":4.8154,"skX":-152.7192,"skY":-152.7192,"x":18.7325}}],"name":"downmouth"}],"name":""}],"ik":[],"animation":[{"zOrder":{"frame":[{"zOrder":[15,-15],"tweenEasing":null,"duration":48},{"zOrder":[15,-15],"tweenEasing":null,"duration":8},{"zOrder":[15,-15],"tweenEasing":null,"duration":4}]},"playTimes":0,"bone":[{"rotateFrame":[],"scaleFrame":[],"name":"root","translateFrame":[]},{"rotateFrame":[{"duration":60}],"scaleFrame":[{"duration":30},{"duration":30}],"name":"deluyi","translateFrame":[]},{"rotateFrame":[],"scaleFrame":[],"name":"leftleg","translateFrame":[]},{"rotateFrame":[],"scaleFrame":[],"name":"rightleg","translateFrame":[]},{"rotateFrame":[{"tweenEasing":0,"duration":30},{"tweenEasing":0,"duration":30,"rotate":-15.199},{"duration":0}],"scaleFrame":[],"name":"rightarm","translateFrame":[]},{"rotateFrame":[{"tweenEasing":0,"duration":30},{"tweenEasing":0,"duration":30,"rotate":15.5186},{"duration":0}],"scaleFrame":[],"name":"leftarm","translateFrame":[]},{"rotateFrame":[{"tweenEasing":0,"duration":30,"rotate":-2.7111},{"tweenEasing":0,"duration":30,"rotate":3.0199},{"duration":0,"rotate":-2.7111}],"scaleFrame":[],"name":"head","translateFrame":[]},{"rotateFrame":[{"tweenEasing":0,"duration":30},{"tweenEasing":0,"duration":30,"rotate":-7.9197},{"duration":0}],"scaleFrame":[],"name":"downmouth","translateFrame":[]},{"rotateFrame":[],"scaleFrame":[{"tweenEasing":0,"duration":17},{"y":0.96,"tweenEasing":0,"duration":13},{"y":0.98,"tweenEasing":0,"duration":30},{"duration":0}],"name":"body","translateFrame":[]}],"slot":[{"colorFrame":[],"displayFrame":[],"name":"leftleg"},{"colorFrame":[],"displayFrame":[],"name":"rightleg"},{"colorFrame":[],"displayFrame":[],"name":"leftarm"},{"colorFrame":[],"displayFrame":[],"name":"body"},{"colorFrame":[],"displayFrame":[],"name":"beard"},{"colorFrame":[],"displayFrame":[],"name":"header"},{"colorFrame":[],"displayFrame":[{"value":1,"duration":24},{"duration":12},{"value":1,"duration":24},{"value":1,"duration":0}],"name":"lefteye_01"},{"colorFrame":[],"displayFrame":[],"name":"rightarm"},{"colorFrame":[],"displayFrame":[],"name":"downmouth"},{"colorFrame":[],"displayFrame":[],"name":"upmouth"},{"colorFrame":[],"displayFrame":[],"name":"desc_04"},{"colorFrame":[],"displayFrame":[],"name":"desc_03"},{"colorFrame":[],"displayFrame":[],"name":"desc_02"},{"colorFrame":[],"displayFrame":[],"name":"desc_01"},{"colorFrame":[],"displayFrame":[{"value":1,"duration":24},{"duration":12},{"value":1,"duration":24},{"value":1,"duration":0}],"name":"righteye_01"},{"colorFrame":[],"displayFrame":[],"name":"weapon"}],"ffd":[],"ik":[],"frame":[],"name":"stay","duration":60},{"zOrder":{"frame":[{"zOrder":[15,-15],"tweenEasing":null,"duration":60}]},"playTimes":0,"bone":[{"rotateFrame":[{"duration":32},{"duration":28}],"scaleFrame":[],"name":"root","translateFrame":[]},{"rotateFrame":[{"duration":32},{"duration":28}],"scaleFrame":[],"name":"deluyi","translateFrame":[]},{"rotateFrame":[{"tweenEasing":0,"duration":30,"rotate":13.0961},{"tweenEasing":0,"duration":30,"rotate":-13.0646},{"duration":0,"rotate":13.0961}],"scaleFrame":[],"name":"leftleg","translateFrame":[{"tweenEasing":0,"duration":30},{"y":61.4063,"tweenEasing":0,"duration":30},{"duration":0}]},{"rotateFrame":[{"tweenEasing":0,"duration":30},{"tweenEasing":0,"duration":30,"rotate":23.7187},{"duration":0}],"scaleFrame":[],"name":"rightleg","translateFrame":[{"tweenEasing":0,"duration":30},{"y":-69.8762,"tweenEasing":0,"duration":30,"x":1.4116},{"duration":0}]},{"rotateFrame":[{"tweenEasing":0,"duration":30,"rotate":75.2794},{"tweenEasing":0,"duration":30,"rotate":-1.3508},{"duration":0,"rotate":75.2794}],"scaleFrame":[],"name":"rightarm","translateFrame":[]},{"rotateFrame":[{"tweenEasing":0,"duration":30,"rotate":-70.2421},{"tweenEasing":0,"duration":30,"rotate":7.8536},{"duration":0,"rotate":-70.2421}],"scaleFrame":[],"name":"leftarm","translateFrame":[]},{"rotateFrame":[{"tweenEasing":0,"duration":16,"rotate":-22.9002},{"tweenEasing":0,"duration":14,"rotate":-13.9421},{"tweenEasing":0,"duration":15,"rotate":4.1437},{"tweenEasing":0,"duration":15,"rotate":-13.9421},{"duration":0,"rotate":-22.9002}],"scaleFrame":[],"name":"head","translateFrame":[]},{"rotateFrame":[{"duration":30},{"duration":30}],"scaleFrame":[{"tweenEasing":0,"duration":15},{"y":0.95,"tweenEasing":0,"duration":15},{"tweenEasing":0,"duration":15},{"y":0.95,"tweenEasing":0,"duration":15},{"duration":0}],"name":"body","translateFrame":[]},{"rotateFrame":[{"duration":32},{"duration":28}],"scaleFrame":[],"name":"downmouth","translateFrame":[]}],"slot":[{"colorFrame":[],"displayFrame":[],"name":"leftleg"},{"colorFrame":[],"displayFrame":[],"name":"rightleg"},{"colorFrame":[],"displayFrame":[],"name":"weapon"},{"colorFrame":[],"displayFrame":[],"name":"leftarm"},{"colorFrame":[],"displayFrame":[],"name":"body"},{"colorFrame":[],"displayFrame":[],"name":"beard"},{"colorFrame":[],"displayFrame":[],"name":"header"},{"colorFrame":[],"displayFrame":[],"name":"lefteye_01"},{"colorFrame":[],"displayFrame":[],"name":"rightarm"},{"colorFrame":[],"displayFrame":[],"name":"downmouth"},{"colorFrame":[],"displayFrame":[],"name":"upmouth"},{"colorFrame":[],"displayFrame":[],"name":"desc_04"},{"colorFrame":[],"displayFrame":[],"name":"desc_03"},{"colorFrame":[],"displayFrame":[],"name":"desc_02"},{"colorFrame":[],"displayFrame":[],"name":"desc_01"},{"colorFrame":[],"displayFrame":[],"name":"righteye_01"}],"ffd":[],"ik":[],"frame":[],"name":"walk","duration":60},{"zOrder":{"frame":[{"zOrder":[7,8,15,-15],"tweenEasing":null,"duration":10},{"zOrder":[7,8,15,-15],"tweenEasing":null,"duration":20},{"zOrder":[7,8,15,-13],"tweenEasing":null,"duration":30},{"zOrder":[7,8,15,-15],"tweenEasing":null,"duration":0}]},"playTimes":0,"bone":[{"rotateFrame":[],"scaleFrame":[],"name":"root","translateFrame":[]},{"rotateFrame":[],"scaleFrame":[],"name":"deluyi","translateFrame":[]},{"rotateFrame":[],"scaleFrame":[],"name":"leftleg","translateFrame":[]},{"rotateFrame":[],"scaleFrame":[],"name":"rightleg","translateFrame":[]},{"rotateFrame":[{"tweenEasing":0,"duration":30},{"tweenEasing":0,"duration":30,"rotate":91.89},{"duration":0}],"scaleFrame":[],"name":"rightarm","translateFrame":[]},{"rotateFrame":[{"tweenEasing":0,"duration":30},{"tweenEasing":0,"duration":30,"rotate":74.9519},{"duration":0}],"scaleFrame":[],"name":"leftarm","translateFrame":[]},{"rotateFrame":[{"tweenEasing":0,"duration":30},{"tweenEasing":0,"duration":30,"rotate":16.5933},{"duration":0}],"scaleFrame":[],"name":"head","translateFrame":[]},{"rotateFrame":[],"scaleFrame":[{"tweenEasing":0,"duration":30},{"y":0.95,"tweenEasing":0,"duration":30},{"duration":0}],"name":"body","translateFrame":[]},{"rotateFrame":[],"scaleFrame":[],"name":"downmouth","translateFrame":[]}],"slot":[{"colorFrame":[],"displayFrame":[],"name":"leftleg"},{"colorFrame":[],"displayFrame":[],"name":"rightleg"},{"colorFrame":[],"displayFrame":[],"name":"weapon"},{"colorFrame":[],"displayFrame":[],"name":"leftarm"},{"colorFrame":[],"displayFrame":[],"name":"body"},{"colorFrame":[],"displayFrame":[],"name":"beard"},{"colorFrame":[],"displayFrame":[],"name":"header"},{"colorFrame":[],"displayFrame":[],"name":"lefteye_01"},{"colorFrame":[],"displayFrame":[],"name":"rightarm"},{"colorFrame":[],"displayFrame":[],"name":"downmouth"},{"colorFrame":[],"displayFrame":[],"name":"upmouth"},{"colorFrame":[],"displayFrame":[],"name":"desc_04"},{"colorFrame":[],"displayFrame":[],"name":"desc_03"},{"colorFrame":[],"displayFrame":[],"name":"desc_02"},{"colorFrame":[],"displayFrame":[],"name":"desc_01"},{"colorFrame":[],"displayFrame":[],"name":"righteye_01"}],"ffd":[],"ik":[],"frame":[],"name":"sk_cure","duration":60},{"zOrder":{"frame":[{"zOrder":[15,-15],"tweenEasing":null,"duration":37},{"zOrder":[15,-15],"tweenEasing":null,"duration":3},{"zOrder":[15,-15],"tweenEasing":null,"duration":20}]},"playTimes":0,"bone":[{"rotateFrame":[],"scaleFrame":[],"name":"root","translateFrame":[]},{"rotateFrame":[],"scaleFrame":[],"name":"deluyi","translateFrame":[]},{"rotateFrame":[],"scaleFrame":[],"name":"leftleg","translateFrame":[]},{"rotateFrame":[],"scaleFrame":[],"name":"rightleg","translateFrame":[]},{"rotateFrame":[{"duration":30},{"tweenEasing":0,"duration":10},{"duration":20,"rotate":-24.1959}],"scaleFrame":[],"name":"rightarm","translateFrame":[]},{"rotateFrame":[{"rotate":118.9369,"duration":30,"curve":[0,0,0.5,1]},{"rotate":118.9369,"duration":10,"curve":[0,0,0.5,1]},{"rotate":53.7307,"duration":10,"curve":[0,0,0.5,1]},{"rotate":63.1606,"duration":10,"curve":[0,0,0.5,1]},{"duration":0}],"scaleFrame":[],"name":"leftarm","translateFrame":[]},{"rotateFrame":[{"duration":30},{"tweenEasing":0,"duration":10},{"duration":20,"rotate":7.6493}],"scaleFrame":[],"name":"head","translateFrame":[]},{"rotateFrame":[],"scaleFrame":[{"curve":[0,0,0.5,1],"duration":30,"x":1.02},{"curve":[0,0,0.5,1],"y":0.95,"duration":10,"x":1.05},{"duration":20}],"name":"body","translateFrame":[]},{"rotateFrame":[{"rotate":-35.0251,"duration":30,"curve":[0,0,0.5,1]},{"rotate":-35.0251,"duration":10,"curve":[0,0,0.5,1]},{"duration":20}],"scaleFrame":[],"name":"downmouth","translateFrame":[]}],"slot":[{"colorFrame":[],"displayFrame":[],"name":"weapon"},{"colorFrame":[],"displayFrame":[],"name":"leftleg"},{"colorFrame":[],"displayFrame":[],"name":"rightleg"},{"colorFrame":[],"displayFrame":[],"name":"leftarm"},{"colorFrame":[],"displayFrame":[],"name":"body"},{"colorFrame":[],"displayFrame":[],"name":"beard"},{"colorFrame":[],"displayFrame":[],"name":"header"},{"colorFrame":[],"displayFrame":[],"name":"lefteye_01"},{"colorFrame":[],"displayFrame":[],"name":"downmouth"},{"colorFrame":[],"displayFrame":[],"name":"upmouth"},{"colorFrame":[],"displayFrame":[],"name":"desc_04"},{"colorFrame":[],"displayFrame":[],"name":"desc_03"},{"colorFrame":[],"displayFrame":[],"name":"desc_02"},{"colorFrame":[],"displayFrame":[],"name":"desc_01"},{"colorFrame":[],"displayFrame":[],"name":"righteye_01"},{"colorFrame":[],"displayFrame":[],"name":"rightarm"}],"ffd":[],"ik":[],"frame":[],"name":"sk_attack","duration":60}],"slot":[{"name":"leftleg","parent":"leftleg","color":{}},{"z":1,"name":"rightleg","parent":"rightleg","color":{}},{"z":2,"name":"leftarm","parent":"leftarm","color":{}},{"z":3,"name":"body","parent":"body","color":{}},{"z":4,"name":"beard","parent":"head","color":{}},{"z":5,"name":"header","parent":"head","color":{}},{"z":6,"displayIndex":1,"name":"lefteye_01","parent":"head","color":{}},{"z":7,"name":"rightarm","parent":"rightarm","color":{}},{"z":8,"name":"downmouth","parent":"downmouth","color":{}},{"z":9,"name":"upmouth","parent":"head","color":{}},{"z":10,"name":"desc_04","parent":"head","color":{}},{"z":11,"name":"desc_03","parent":"head","color":{}},{"z":12,"name":"desc_02","parent":"head","color":{}},{"z":13,"name":"desc_01","parent":"head","color":{}},{"z":14,"displayIndex":1,"name":"righteye_01","parent":"head","color":{}},{"z":15,"name":"weapon","parent":"body","color":{}}],"frameRate":60,"defaultActions":[{"gotoAndPlay":"stay"}]}],"name":"deluyi","version":"5.5"}